jupyterlab_gist_it/__init__.py
jupyterlab_gist_it/_version.py
jupyterlab_gist_it-0.2.1.data/data/share/jupyter/labextensions/jupyterlab_gist_it/package.json
jupyterlab_gist_it-0.2.1.data/data/share/jupyter/labextensions/jupyterlab_gist_it/schemas/jupyterlab_gist_it/package.json.orig
jupyterlab_gist_it-0.2.1.data/data/share/jupyter/labextensions/jupyterlab_gist_it/schemas/jupyterlab_gist_it/settings.json
jupyterlab_gist_it-0.2.1.data/data/share/jupyter/labextensions/jupyterlab_gist_it/static/74.30ef7558a907e6c53fbf.js
jupyterlab_gist_it-0.2.1.data/data/share/jupyter/labextensions/jupyterlab_gist_it/static/747.21f6f6361f0ce7dcceb5.js
jupyterlab_gist_it-0.2.1.data/data/share/jupyter/labextensions/jupyterlab_gist_it/static/849.8f31eacb234a103ec77b.js
jupyterlab_gist_it-0.2.1.data/data/share/jupyter/labextensions/jupyterlab_gist_it/static/849.8f31eacb234a103ec77b.js.LICENSE.txt
jupyterlab_gist_it-0.2.1.data/data/share/jupyter/labextensions/jupyterlab_gist_it/static/remoteEntry.744eb2413ea92619ece2.js
jupyterlab_gist_it-0.2.1.data/data/share/jupyter/labextensions/jupyterlab_gist_it/static/style.js
jupyterlab_gist_it-0.2.1.data/data/share/jupyter/labextensions/jupyterlab_gist_it/static/third-party-licenses.json
jupyterlab_gist_it-0.2.1.data/data/share/jupyter/labextensions/jupyterlab_gist_it/install.json
jupyterlab_gist_it-0.2.1.dist-info/METADATA
jupyterlab_gist_it-0.2.1.dist-info/WHEEL
jupyterlab_gist_it-0.2.1.dist-info/licenses/LICENSE
jupyterlab_gist_it-0.2.1.dist-info/RECORD
