Metadata-Version: 2.1
Name: jupyterlab_gist_it
Version: 0.2.1
Summary: Upload Jupyter notebooks to GitHub Gist.
Project-URL: Homepage, https://github.com/adrn/jupyterlab-gist-it
Project-URL: Bug Tracker, https://github.com/adrn/jupyterlab-gist-it/issues
Project-URL: Repository, https://github.com/adrn/jupyterlab-gist-it.git
Author-email: adrn <adrianmpw@gmail.com>
License: BSD 3-Clause License
License-File: LICENSE
Classifier: Framework :: Jupyter
Classifier: Framework :: Jupyter :: JupyterLab
Classifier: Framework :: Jupyter :: JupyterLab :: 4
Classifier: Framework :: Jupyter :: JupyterLab :: Extensions
Classifier: Framework :: Jupyter :: JupyterLab :: Extensions :: Prebuilt
Classifier: License :: OSI Approved :: BSD License
Classifier: Programming Language :: Python
Classifier: Programming Language :: Python :: 3
Classifier: Programming Language :: Python :: 3.8
Classifier: Programming Language :: Python :: 3.9
Classifier: Programming Language :: Python :: 3.10
Classifier: Programming Language :: Python :: 3.11
Requires-Python: >=3.8
